README.md
setup.py
ark/__init__.py
ark/apps.py
ark/constants.py
ark/converter.py
ark/filters.py
ark/models.py
ark/node_manager.py
ark/router.py
ark/schema.py
ark/tests.py
ark/transactions.py
ark/types.py
ark/migrations/0001_initial.py
ark/migrations/__init__.py
django_ark.egg-info/PKG-INFO
django_ark.egg-info/SOURCES.txt
django_ark.egg-info/dependency_links.txt
django_ark.egg-info/requires.txt
django_ark.egg-info/top_level.txt