Metadata-Version: 1.0
Name: django-ark
Version: 0.1.3
Summary: ark blockchain integration with Django
Home-page: https://github.com/BlockHub/django-ark
Author: Charles
Author-email: karel@blockhub.nl
License: MIT
Platform: UNKNOWN
